jwallet/__init__.py
jwallet/jwallet.py
jwallet-0.1.17.dist-info/LICENSE
jwallet-0.1.17.dist-info/METADATA
jwallet-0.1.17.dist-info/WHEEL
jwallet-0.1.17.dist-info/entry_points.txt
jwallet-0.1.17.dist-info/top_level.txt
jwallet-0.1.17.dist-info/RECORD
