Metadata-Version: 2.1
Name: jwallet
Version: 0.1.17
Summary: A CLI crypto wallet generator
Home-page: https://github.com/jasonknoll/jwallet
Author: Jason Knoll
Author-email: jknolldev@gmail.com
License: MIT
Classifier: Programming Language :: Python :: 3
Classifier: License :: OSI Approved :: MIT License
Classifier: Operating System :: OS Independent
Requires-Python: >=3.8
License-File: LICENSE
Requires-Dist: web3
Requires-Dist: argparse
Requires-Dist: python-dotenv
Requires-Dist: bitcoinlib
Requires-Dist: eth-account
